temet/__init__.py
temet/test.py
temet/ICs/ResimMakePartLoad.py
temet/ICs/__init__.py
temet/ICs/coffee.py
temet/ICs/coffee_readSpoonMesh.py
temet/ICs/halo_Hernquist.py
temet/ICs/halo_NFW.py
temet/ICs/halo_NFW_tracers.py
temet/ICs/kelvin_helmholtz.py
temet/ICs/sedov_solution.py
temet/ICs/shocks2d.py
temet/ICs/sod_solution.py
temet/ICs/utilities.py
temet/ICs/yee_vortex.py
temet/ML/__init__.py
temet/ML/common.py
temet/ML/explore.py
temet/ML/smhm.py
temet/ML/smhm_sbi.py
temet/ML/spectra.py
temet/catalog/__init__.py
temet/catalog/box.py
temet/catalog/common.py
temet/catalog/gasflows.py
temet/catalog/group.py
temet/catalog/maps.py
temet/catalog/profile.py
temet/catalog/subhalo.py
temet/catalog/temporal.py
temet/cosmo/__init__.py
temet/cosmo/cloudy.py
temet/cosmo/cloudyGrid.py
temet/cosmo/clustering.py
temet/cosmo/color.py
temet/cosmo/cooling.py
temet/cosmo/hydrogen.py
temet/cosmo/kCorr.py
temet/cosmo/lightcone.py
temet/cosmo/mergertree.py
temet/cosmo/skirt.py
temet/cosmo/stellarPop.py
temet/cosmo/time_evo.py
temet/cosmo/util.py
temet/cosmo/xray.py
temet/cosmo/zooms.py
temet/cosmo/zoomsVirtualBox.py
temet/data/adami/xxl_365_gc.txt
temet/data/arnaud/chexmate.txt
temet/data/baldry/README.txt
temet/data/baldry/gs-ratios.txt
temet/data/baldry/gsmf-B12.txt
temet/data/baldry/gsmf-BGD08.txt
temet/data/baldry/size-mass.txt
temet/data/behroozi/README.txt
temet/data/behroozi/analysis/sfr_corrected_10.0.dat
temet/data/behroozi/analysis/sfr_corrected_10.2.dat
temet/data/behroozi/analysis/sfr_corrected_10.4.dat
temet/data/behroozi/analysis/sfr_corrected_10.6.dat
temet/data/behroozi/analysis/sfr_corrected_10.8.dat
temet/data/behroozi/analysis/sfr_corrected_11.0.dat
temet/data/behroozi/analysis/sfr_corrected_11.2.dat
temet/data/behroozi/analysis/sfr_corrected_11.4.dat
temet/data/behroozi/analysis/sfr_corrected_11.6.dat
temet/data/behroozi/analysis/sfr_corrected_11.8.dat
temet/data/behroozi/analysis/sfr_corrected_12.0.dat
temet-0.9.0.dist-info/METADATA
temet-0.9.0.dist-info/WHEEL
temet-0.9.0.dist-info/RECORD
temet-0.9.0.dist-info/licenses/LICENSE.md
temet-0.9.0.dist-info/sboms/auditwheel.cdx.json
