Metadata-Version: 2.4
Name: temet
Version: 0.9.0
Summary: temet simulation analysis framework.
Keywords: astronomy,simulation,cosmology,astrophysics
Author-Email: Dylan Nelson <dnelson@uni-heidelberg.de>
License-Expression: MIT
Classifier: Development Status :: 4 - Beta
Classifier: Intended Audience :: Science/Research
Classifier: Operating System :: OS Independent
Classifier: Programming Language :: Python :: 3
Classifier: Programming Language :: Python :: 3.11
Classifier: Programming Language :: Python :: 3.12
Classifier: Programming Language :: Python :: 3.13
Classifier: Topic :: Scientific/Engineering :: Astronomy
Classifier: Topic :: Scientific/Engineering :: Physics
Project-URL: Homepage, https://www.github.com/dnelson/temet/
Project-URL: Bug Tracker, https://www.github.com/dnelson/temet/issues
Project-URL: Documentation, https://temet.tng-project.org/
Requires-Python: >3.11.0
Requires-Dist: astropy
Requires-Dist: cmocean
Requires-Dist: h5py
Requires-Dist: healpy
Requires-Dist: matplotlib
Requires-Dist: numba
Requires-Dist: numpy
Requires-Dist: scipy
Requires-Dist: pybind11
Requires-Dist: illustris_python
Provides-Extra: test
Requires-Dist: pytest; extra == "test"
Requires-Dist: pytest-cov; extra == "test"
Requires-Dist: pytest-benchmark; extra == "test"
Provides-Extra: dev
Requires-Dist: buildbot; extra == "dev"
Requires-Dist: pyslurm; extra == "dev"
Requires-Dist: torch; extra == "dev"
Requires-Dist: torchvision; extra == "dev"
Requires-Dist: tensorboard; extra == "dev"
Requires-Dist: sbi; extra == "dev"
Requires-Dist: reproject; extra == "dev"
Requires-Dist: astro-sedpy; extra == "dev"
Requires-Dist: astro-prospector; extra == "dev"
Requires-Dist: scikit-image; extra == "dev"
Requires-Dist: corner; extra == "dev"
Requires-Dist: emcee; extra == "dev"
Requires-Dist: healpy; extra == "dev"
Requires-Dist: psutil; extra == "dev"
Requires-Dist: pygrackle; extra == "dev"
Provides-Extra: docs
Requires-Dist: sphinx; extra == "docs"
Requires-Dist: breathe; extra == "docs"
Requires-Dist: exhale; extra == "docs"
